[
  {
    "nama_kelas": "Python Fundamentals Bootcamp",
    "deskripsi": "Learn the basics of Python programming, including data types, control flow, and functions.",
    "tanggal_mulai": "2023-10-01",
    "tanggal_berakhir": "2023-10-15"
  },
  {
    "nama_kelas": "Advanced JavaScript Bootcamp",
    "deskripsi": "Dive deep into JavaScript concepts like asynchronous programming, closures, and modern frameworks.",
    "tanggal_mulai": "2023-11-01",
    "tanggal_berakhir": "2023-11-15"
  },
  {
    "nama_kelas": "Data Science with Python",
    "deskripsi": "Explore data analysis, visualization, and machine learning using Python libraries like Pandas, NumPy, and Scikit-learn.",
    "tanggal_mulai": "2023-10-16",
    "tanggal_berakhir": "2023-10-30"
  },
  {
    "nama_kelas": "Full-Stack Web Development",
    "deskripsi": "Build dynamic web applications from front-end to back-end using modern technologies.",
    "tanggal_mulai": "2023-11-16",
    "tanggal_berakhir": "2023-11-30"
  },
  {
    "nama_kelas": "React.js Mastery",
    "deskripsi": "Master the React library for building interactive user interfaces.",
    "tanggal_mulai": "2023-12-01",
    "tanggal_berakhir": "2023-12-15"
  },
  {
    "nama_kelas": "Node.js Backend Development",
    "deskripsi": "Develop robust server-side applications with Node.js and Express.",
    "tanggal_mulai": "2023-12-16",
    "tanggal_berakhir": "2023-12-30"
  },
  {
    "nama_kelas": "Mobile App Development with Flutter",
    "deskripsi": "Create cross-platform mobile applications using the Flutter framework.",
    "tanggal_mulai": "2024-01-01",
    "tanggal_berakhir": "2024-01-15"
  },
  {
    "nama_kelas": "Cloud Computing Essentials",
    "deskripsi": "Understand the fundamentals of cloud platforms like AWS, Azure, and Google Cloud.",
    "tanggal_mulai": "2024-01-16",
    "tanggal_berakhir": "2024-01-30"
  },
  {
    "nama_kelas": "DevOps Fundamentals",
    "deskripsi": "Learn principles and practices for continuous integration and continuous delivery.",
    "tanggal_mulai": "2024-02-01",
    "tanggal_berakhir": "2024-02-15"
  },
  {
    "nama_kelas": "Cybersecurity Basics",
    "deskripsi": "Introduction to cybersecurity concepts, threats, and defense mechanisms.",
    "tanggal_mulai": "2024-02-16",
    "tanggal_berakhir": "2024-02-29"
  },
  {
    "nama_kelas": "Machine Learning Engineering",
    "deskripsi": "Build and deploy machine learning models in production environments.",
    "tanggal_mulai": "2024-03-01",
    "tanggal_berakhir": "2024-03-15"
  },
  {
    "nama_kelas": "Artificial Intelligence Fundamentals",
    "deskripsi": "Explore the core concepts of artificial intelligence and its applications.",
    "tanggal_mulai": "2024-03-16",
    "tanggal_berakhir": "2024-03-30"
  },
  {
    "nama_kelas": "Database Management with SQL",
    "deskripsi": "Learn to design, query, and manage relational databases using SQL.",
    "tanggal_mulai": "2024-04-01",
    "tanggal_berakhir": "2024-04-15"
  },
  {
    "nama_kelas": "NoSQL Database Design",
    "deskripsi": "Understand and implement databases like MongoDB and Cassandra.",
    "tanggal_mulai": "2024-04-16",
    "tanggal_berakhir": "2024-04-30"
  },
  {
    "nama_kelas": "Game Development with Unity",
    "deskripsi": "Create 2D and 3D games using the Unity game engine and C#.",
    "tanggal_mulai": "2024-05-01",
    "tanggal_berakhir": "2024-05-15"
  },
  {
    "nama_kelas": "UI/UX Design Principles",
    "deskripsi": "Learn the fundamentals of user interface and user experience design.",
    "tanggal_mulai": "2024-05-16",
    "tanggal_berakhir": "2024-05-30"
  },
  {
    "nama_kelas": "Agile Project Management",
    "deskripsi": "Understand and apply agile methodologies for software development projects.",
    "tanggal_mulai": "2024-06-01",
    "tanggal_berakhir": "2024-06-15"
  },
  {
    "nama_kelas": "Technical Writing for Developers",
    "deskripsi": "Learn to create clear and effective technical documentation.",
    "tanggal_mulai": "2024-06-16",
    "tanggal_berakhir": "2024-06-30"
  },
  {
    "nama_kelas": "Business Analysis Fundamentals",
    "deskripsi": "Develop skills for analyzing business needs and recommending solutions.",
    "tanggal_mulai": "2024-07-01",
    "tanggal_berakhir": "2024-07-15"
  },
  {
    "nama_kelas": "Quality Assurance Testing",
    "deskripsi": "Learn to design and execute software tests to ensure quality.",
    "tanggal_mulai": "2024-07-16",
    "tanggal_berakhir": "2024-07-30"
  }
]
